sarscov2/__init__.py
sarscov2/admin_site.py
sarscov2/apps.py
sarscov2/asgi.py
sarscov2/baker_recipes.py
sarscov2/choices.py
sarscov2/constants.py
sarscov2/settings.py
sarscov2/urls.py
sarscov2/wsgi.py
sarscov2/admin/__init__.py
sarscov2/admin/coronavirus_kap_admin.py
sarscov2/admin/modeladmin_mixin.py
sarscov2/auth/__init__.py
sarscov2/auth/codenames.py
sarscov2/forms/__init__.py
sarscov2/forms/coronavirus_kap_form.py
sarscov2/forms/coronavirus_kap_form_validator.py
sarscov2/migrations/0001_initial.py
sarscov2/migrations/0002_auto_20200416_1937.py
sarscov2/migrations/0003_auto_20200515_0231.py
sarscov2/migrations/0004_delete_coronakapinformationsources.py
sarscov2/migrations/0005_auto_20200527_1448.py
sarscov2/migrations/0006_auto_20200527_2155.py
sarscov2/migrations/0007_alter_coronaviruskap_options.py
sarscov2/migrations/__init__.py
sarscov2/model_mixins/__init__.py
sarscov2/model_mixins/coronavirus_kap_model_mixin.py
sarscov2/models/__init__.py
sarscov2/models/coronavirus_kap.py
sarscov2/tests/__init__.py
sarscov2/tests/sites.py
sarscov2/tests/tests.py
sarscov2-0.1.15.dist-info/LICENSE
sarscov2-0.1.15.dist-info/METADATA
sarscov2-0.1.15.dist-info/WHEEL
sarscov2-0.1.15.dist-info/top_level.txt
sarscov2-0.1.15.dist-info/RECORD
